pyshortener/__init__.py
pyshortener/main.py
pyshortener-1.2.2.dist-info/LICENSE
pyshortener-1.2.2.dist-info/METADATA
pyshortener-1.2.2.dist-info/WHEEL
pyshortener-1.2.2.dist-info/top_level.txt
pyshortener-1.2.2.dist-info/RECORD
