Metadata-Version: 2.1
Name: pyshortener
Version: 1.2.2
Summary: A Python package for interacting with the is.gd and v.gd API
Author: Hamster45105
License: MIT License
Project-URL: Homepage, https://github.com/Hamster45105/pyshortener
Project-URL: Issues, https://github.com/Hamster45105/pyshortener/issues
Project-URL: Pull Requests, https://github.com/Hamster45105/pyshortener/pulls
Project-URL: Documentation, https://github.com/Hamster45105/pyshortener/blob/main/DOCS.md
Keywords: url shortener,is.gd,v.gd
Classifier: Programming Language :: Python
Classifier: Programming Language :: Python :: 3
Classifier: Programming Language :: Python :: 3.8
Classifier: Programming Language :: Python :: 3.9
Classifier: Programming Language :: Python :: 3.10
Classifier: Programming Language :: Python :: 3.11
Classifier: Programming Language :: Python :: 3.12
Classifier: License :: OSI Approved :: MIT License
Classifier: Development Status :: 5 - Production/Stable
Classifier: Intended Audience :: Developers
Classifier: Topic :: Software Development :: Libraries
Classifier: Topic :: Software Development :: Libraries :: Python Modules
Classifier: Operating System :: OS Independent
Classifier: Natural Language :: English
Requires-Python: >=3.8
License-File: LICENSE
Requires-Dist: requests==2.32.3
